nonebot_plugin_aujob/__init__.py
nonebot_plugin_aujob/utils.py
nonebot_plugin_aujob-1.1.514.dist-info/METADATA
nonebot_plugin_aujob-1.1.514.dist-info/WHEEL
nonebot_plugin_aujob-1.1.514.dist-info/top_level.txt
nonebot_plugin_aujob-1.1.514.dist-info/RECORD
