Metadata-Version: 2.1
Name: nonebot-plugin-aujob
Version: 1.1.514
Summary: A nonebot plugin
Author-email: qwqZYLqwq <3422471182@qq.com>
Project-URL: Homepage, https://github.com/qwqZYLqwq/nonebot-plugin-aujob
Project-URL: Bug Tracker, https://github.com/qwqZYLqwq/nonebot-plugin-aujob/issues
Classifier: Programming Language :: Python :: 3
Classifier: License :: OSI Approved :: MIT License
Classifier: Operating System :: OS Independent
Requires-Python: >=3.8
Requires-Dist: nonebot2 (>=2.0.0)
